smartshell.py
smartshell_ease/__init__.py
smartshell_ease/commands.json
smartshell_ease/smartshell.py
smartshell_ease-0.1.dist-info/METADATA
smartshell_ease-0.1.dist-info/WHEEL
smartshell_ease-0.1.dist-info/entry_points.txt
smartshell_ease-0.1.dist-info/top_level.txt
smartshell_ease-0.1.dist-info/RECORD
