Metadata-Version: 2.4
Name: smartshell-ease
Version: 0.1
Classifier: Programming Language :: Python :: 3
Classifier: License :: OSI Approved :: MIT License
Classifier: Operating System :: OS Independent
Requires-Python: >=3.6
Requires-Dist: click
Requires-Dist: colorama
Requires-Dist: rich
Requires-Dist: requests
Requires-Dist: rapidfuzz
Requires-Dist: openai
Requires-Dist: ollama
Requires-Dist: pyreadline3
Dynamic: classifier
Dynamic: description
Dynamic: description-content-type
Dynamic: requires-dist
Dynamic: requires-python
